relaton_bib/__init__.py
relaton_bib/address.py
relaton_bib/affiliation.py
relaton_bib/bib_item_locality.py
relaton_bib/biblio_note.py
relaton_bib/biblio_version.py
relaton_bib/bibliographic_date.py
relaton_bib/bibliographic_item.py
relaton_bib/bibtex_parser.py
relaton_bib/classification.py
relaton_bib/contact.py
relaton_bib/contribution_info.py
relaton_bib/contributor.py
relaton_bib/copyright_association.py
relaton_bib/dict_parser.py
relaton_bib/document_identifier.py
relaton_bib/document_relation.py
relaton_bib/document_relation_collection.py
relaton_bib/document_status.py
relaton_bib/editorial_group.py
relaton_bib/formatted_ref.py
relaton_bib/formatted_string.py
relaton_bib/hit.py
relaton_bib/hit_collection.py
relaton_bib/ics.py
relaton_bib/localized_string.py
relaton_bib/medium.py
relaton_bib/organization.py
relaton_bib/person.py
relaton_bib/place.py
relaton_bib/relaton_bib.py
relaton_bib/series.py
relaton_bib/structured_identifier.py
relaton_bib/technical_committee.py
relaton_bib/typed_title_string.py
relaton_bib/typed_uri.py
relaton_bib/validity.py
relaton_bib/workgroup.py
relaton_bib/xml_parser.py
relaton_bib-0.2.0.dist-info/AUTHORS.rst
relaton_bib-0.2.0.dist-info/LICENSE
relaton_bib-0.2.0.dist-info/METADATA
relaton_bib-0.2.0.dist-info/WHEEL
relaton_bib-0.2.0.dist-info/top_level.txt
relaton_bib-0.2.0.dist-info/RECORD
