Metadata-Version: 2.1
Name: relaton_bib
Version: 0.2.0
Summary: Python implementation of bibliography specification
Home-page: https://github.com/relaton/relaton-bib-py
Author: Aliaksandr Babrykovich
Author-email: abobrikovich@gmail.com
License: BSD license
Keywords: relaton_bib
Platform: UNKNOWN
Classifier: Development Status :: 2 - Pre-Alpha
Classifier: Intended Audience :: Developers
Classifier: License :: OSI Approved :: BSD License
Classifier: Natural Language :: English
Classifier: Programming Language :: Python :: 3
Classifier: Programming Language :: Python :: 3.6
Classifier: Programming Language :: Python :: 3.7
Classifier: Programming Language :: Python :: 3.8
Requires-Python: >=3.8
License-File: LICENSE
License-File: AUTHORS.rst
